<teiTrim>
<header>
<meta key="page" value="832"/>
<meta key="seq" value=""/>
<meta key="pid" value="INT_307917d8-c496-32de-8a78-85fab58791db"/>
<meta key="title" value="Toelichting bij de indices"/>
</header>

<body>
<pb n="832" />
<p rend="font-size: 14; font-weight: bold; line-height: 15.5pt">Toelichting bij de indices<lb/>
</p>
<p rend="font-size: 11; line-height: 14.4pt"><hi rend="font-size:11; font-family:Liberation Serif; font-style:italic">Cursief</hi> gedrukt zijn de bladzijden, waarop naar een woord in de noten wordt verwezen.<lb/>
Woorden als Buginezen, Chinezen of Engelsen zoeke men in de Index van overige termen.<lb/>
De schrijvers der Generale Missiven hebben eigennamen (van mensen, plaatsen, schepen<lb/>
enz.) zonder enig systeem en op de meest uiteenlopende wijze gespeld, wat vooral bij<lb/>
niet-Europese termen tot verwarring kan leiden. Waar die kans groot is, zijn de verschillende<lb/>
schrijfwijzen in de indices opgenomen, met verwijzing naar de schrijfwijze waarbij<lb/>
de bladzijden aangegeven zijn.<lb/>
</p>
<p rend="font-size: 11; line-height: 14.4pt">Geografische namen zijn, waar mogelijk, opgenomen in moderne schrijfwijze. Voor<lb/>
scheepsnamen is de schrijfwijze in
<hi rend="font-size:11; font-family:Liberation Serif; font-style:italic">DAS</hi> gevolgd.<lb/>
</p>
<table>
<row><cell>
<p rend="font-size: 16; line-height: 17.7pt">c<lb/>
</p>
</cell><cell>
<p rend="font-size: 11; line-height: 12.2pt">bij K en S<lb/>
</p>
</cell><cell>
<p rend="font-size: 11; text-align: right; line-height: 12.2pt; margin-right: 800">Ph<lb/>
</p>
</cell><cell>
<p rend="font-size: 11; line-height: 12.2pt">bij F en V<lb/>
</p>
</cell>
</row>
<row><cell>
<p rend="font-size: 11; line-height: 12.2pt">Ch<lb/>
</p>
</cell><cell>
<p rend="font-size: 11; line-height: 12.2pt">bij G, Ts en Tsj<lb/>
</p>
</cell><cell>
<p rend="font-size: 11; text-align: right; line-height: 12.2pt; margin-right: 800">0<lb/>
</p>
</cell><cell>
<p rend="font-size: 11; line-height: 12.2pt">bij K<lb/>
</p>
</cell>
</row>
<row><cell>
<p rend="font-size: 11; line-height: 12.2pt">Dj<lb/>
</p>
</cell><cell>
<p rend="font-size: 11; line-height: 12.2pt">bij J<lb/>
</p>
</cell><cell>
<p rend="font-size: 11; text-align: right; line-height: 12.2pt; margin-right: 1300">S<lb/>
</p>
</cell><cell>
<p rend="font-size: 11; line-height: 12.2pt">bij C en Z<lb/>
</p>
</cell>
</row>
<row><cell>
<p rend="font-size: 11; line-height: 12.2pt">F<lb/>
</p>
</cell><cell>
<p rend="font-size: 11; line-height: 12.2pt">bij Ph en V<lb/>
</p>
</cell><cell>
<p rend="font-size: 11; text-align: right; line-height: 12.2pt; margin-right: 800">Ts<lb/>
</p>
</cell><cell>
<p rend="font-size: 11; line-height: 12.2pt">bij Ch en Tsj<lb/>
</p>
</cell>
</row>
<row><cell>
<p rend="font-size: 11; line-height: 12.2pt">G<lb/>
</p>
</cell><cell>
<p rend="font-size: 11; line-height: 12.2pt">bij Ch<lb/>
</p>
</cell><cell>
<p rend="font-size: 11; text-align: right; line-height: 12.2pt; margin-right: 800">Tsj<lb/>
</p>
</cell><cell>
<p rend="font-size: 11; line-height: 12.2pt">bij Ch en Ts<lb/>
</p>
</cell>
</row>
<row><cell>
<p rend="font-size: 11; line-height: 12.2pt">J<lb/>
</p>
</cell><cell>
<p rend="font-size: 11; line-height: 12.2pt">bij Dj<lb/>
</p>
</cell><cell>
<p rend="font-size: 11; text-align: right; line-height: 12.2pt; margin-right: 800">V<lb/>
</p>
</cell><cell>
<p rend="font-size: 11; line-height: 12.2pt">bij F en Ph<lb/>
</p>
</cell>
</row>
<row><cell>
<p rend="font-size: 16; line-height: 17.7pt">K<lb/>
</p>
</cell><cell>
<p rend="font-size: 11; line-height: 12.2pt">bij C en 0<lb/>
</p>
</cell><cell>
<p rend="font-size: 16; text-align: right; line-height: 17.7pt; margin-right: 800">z<lb/>
</p>
</cell><cell>
<p rend="font-size: 11; line-height: 12.2pt">bij C en S<lb/>
</p>
</cell>
</row>
</table>
<fw type="bottom-page-number">832
</fw>
</body>
</teiTrim>