<teiTrim>
<header>

<meta key="page" value="118"/>
<meta key="title" value="Coen, De Carpentier, Van Antzen, Specx, Batavia, 6 september 1622"/>
<meta key="rawdate" value="6 september 1622"/>
<meta key="seq" value="XIX"/>
<meta key="place" value="Batavia"/>
<meta key="year" value="1622"/>
<meta key="month" value="9"/>
<meta key="day" value="6"/>
<meta key="author" value="Coen, De Carpentier, Van Antzen, Specx"/>

</header>
<body>
<head>XIX. JAN PIETERSZ. COEN, PIETER DE CARPENTIER, WILLEM VAN<lb/>
ANTZEN EN JACQUES SPECX, BATAVIA 6 september 1622.<lb/>
</head>
<note place="inline" type="editorial-summary" resp="editor" rend="italic indent">
(Afgedrukt <hi>Coen</hi> I, p. 718-754).<lb/>
</note>
</body>
</teiTrim>